{"__symbolic":"module","version":3,"exports":[{"from":"@syncfusion/ej2-navigations"}],"metadata":{"ɵa":["animation","dataSource","enableHtmlSanitizer","enablePersistence","enableRtl","expandMode","expandedIndices","headerTemplate","height","itemTemplate","items","locale","width"],"ɵb":["clicked","created","destroyed","expanded","expanding","expandedIndicesChange"],"ɵc":["allowKeyboard","cssClass","enableCollision","enableHtmlSanitizer","enablePersistence","enableRtl","height","items","locale","overflowMode","scrollStep","width"],"ɵd":["beforeCreate","clicked","created","destroyed"],"ɵe":["animationSettings","cssClass","enableHtmlSanitizer","enablePersistence","enableRtl","enableScrolling","fields","filter","items","locale","showItemOnClick","target","template"],"ɵf":["beforeClose","beforeItemRender","beforeOpen","created","onClose","onOpen","select"],"ɵg":["animation","cssClass","enableHtmlSanitizer","enablePersistence","enableRtl","headerPlacement","height","heightAdjustMode","items","loadOn","locale","overflowMode","scrollStep","selectedItem","showCloseButton","width"],"ɵh":["added","adding","created","destroyed","removed","removing","selected","selecting"],"ɵi":["allowDragAndDrop","allowEditing","allowMultiSelection","animation","autoCheck","checkedNodes","cssClass","disabled","dragArea","enableHtmlSanitizer","enablePersistence","enableRtl","expandOn","expandedNodes","fields","fullRowNavigable","fullRowSelect","loadOnDemand","locale","nodeTemplate","selectedNodes","showCheckBox","sortOrder"],"ɵj":["actionFailure","created","dataBound","dataSourceChanged","destroyed","drawNode","keyPress","nodeChecked","nodeChecking","nodeClicked","nodeCollapsed","nodeCollapsing","nodeDragStart","nodeDragStop","nodeDragging","nodeDropped","nodeEdited","nodeEditing","nodeExpanded","nodeExpanding","nodeSelected","nodeSelecting"],"ɵk":["animate","closeOnDocumentClick","dockSize","enableDock","enableGestures","enablePersistence","enableRtl","height","isOpen","locale","mediaQuery","position","showBackdrop","target","type","width","zIndex"],"ɵl":["change","close","created","destroyed","open","isOpenChange"],"ɵm":["animationSettings","cssClass","enableHtmlSanitizer","enablePersistence","enableRtl","enableScrolling","fields","filter","hamburgerMode","items","locale","orientation","showItemOnClick","target","template","title"],"ɵn":["beforeClose","beforeItemRender","beforeOpen","created","onClose","onOpen","select"],"AccordionItemDirective":{"__symbolic":"class","extends":{"__symbolic":"reference","module":"@syncfusion/ej2-angular-base","name":"ComplexBase"},"decorators":[{"__symbolic":"call","expression":{"__symbolic":"reference","module":"@angular/core","name":"Directive"},"arguments":[{"selector":"e-accordionitems>e-accordionitem","inputs":["content","cssClass","disabled","expanded","header","iconCss","visible"],"outputs":[],"queries":{}}]}],"members":{"header":[{"__symbolic":"property","decorators":[{"__symbolic":"call","expression":{"__symbolic":"reference","module":"@angular/core","name":"ContentChild"},"arguments":["header"]},{"__symbolic":"call","expression":{"__symbolic":"reference","module":"@syncfusion/ej2-angular-base","name":"Template"}}]}],"content":[{"__symbolic":"property","decorators":[{"__symbolic":"call","expression":{"__symbolic":"reference","module":"@angular/core","name":"ContentChild"},"arguments":["content"]},{"__symbolic":"call","expression":{"__symbolic":"reference","module":"@syncfusion/ej2-angular-base","name":"Template"}}]}],"__ctor__":[{"__symbolic":"constructor","parameters":[{"__symbolic":"reference","module":"@angular/core","name":"ViewContainerRef"}]}]}},"AccordionItemsDirective":{"__symbolic":"class","extends":{"__symbolic":"reference","module":"@syncfusion/ej2-angular-base","name":"ArrayBase"},"decorators":[{"__symbolic":"call","expression":{"__symbolic":"reference","module":"@angular/core","name":"Directive"},"arguments":[{"selector":"ejs-accordion>e-accordionitems","queries":{"children":{"__symbolic":"new","expression":{"__symbolic":"reference","module":"@angular/core","name":"ContentChildren"},"arguments":[{"__symbolic":"reference","name":"AccordionItemDirective"}]}}}]}],"members":{"__ctor__":[{"__symbolic":"constructor"}]}},"AccordionComponent":{"__symbolic":"class","extends":{"__symbolic":"reference","module":"@syncfusion/ej2-navigations","name":"Accordion"},"decorators":[{"__symbolic":"call","expression":{"__symbolic":"reference","module":"@angular/core","name":"Component"},"arguments":[{"selector":"ejs-accordion","inputs":{"__symbolic":"reference","name":"ɵa"},"outputs":{"__symbolic":"reference","name":"ɵb"},"template":"<ng-content select='div'></ng-content>","changeDetection":{"__symbolic":"select","expression":{"__symbolic":"reference","module":"@angular/core","name":"ChangeDetectionStrategy"},"member":"OnPush"},"queries":{"childItems":{"__symbolic":"new","expression":{"__symbolic":"reference","module":"@angular/core","name":"ContentChild"},"arguments":[{"__symbolic":"reference","name":"AccordionItemsDirective"}]}}}]},{"__symbolic":"call","expression":{"__symbolic":"reference","module":"@syncfusion/ej2-angular-base","name":"ComponentMixins"},"arguments":[[{"__symbolic":"reference","module":"@syncfusion/ej2-angular-base","name":"ComponentBase"}]]}],"members":{"headerTemplate":[{"__symbolic":"property","decorators":[{"__symbolic":"call","expression":{"__symbolic":"reference","module":"@angular/core","name":"ContentChild"},"arguments":["headerTemplate"]},{"__symbolic":"call","expression":{"__symbolic":"reference","module":"@syncfusion/ej2-angular-base","name":"Template"}}]}],"itemTemplate":[{"__symbolic":"property","decorators":[{"__symbolic":"call","expression":{"__symbolic":"reference","module":"@angular/core","name":"ContentChild"},"arguments":["itemTemplate"]},{"__symbolic":"call","expression":{"__symbolic":"reference","module":"@syncfusion/ej2-angular-base","name":"Template"}}]}],"__ctor__":[{"__symbolic":"constructor","parameters":[{"__symbolic":"reference","module":"@angular/core","name":"ElementRef"},{"__symbolic":"reference","module":"@angular/core","name":"Renderer2"},{"__symbolic":"reference","module":"@angular/core","name":"ViewContainerRef"},{"__symbolic":"reference","module":"@angular/core","name":"Injector"}]}],"ngOnInit":[{"__symbolic":"method"}],"ngAfterViewInit":[{"__symbolic":"method"}],"ngOnDestroy":[{"__symbolic":"method"}],"ngAfterContentChecked":[{"__symbolic":"method"}]}},"AccordionModule":{"__symbolic":"class","decorators":[{"__symbolic":"call","expression":{"__symbolic":"reference","module":"@angular/core","name":"NgModule"},"arguments":[{"imports":[{"__symbolic":"reference","module":"@angular/common","name":"CommonModule"}],"declarations":[{"__symbolic":"reference","name":"AccordionComponent"},{"__symbolic":"reference","name":"AccordionItemDirective"},{"__symbolic":"reference","name":"AccordionItemsDirective"}],"exports":[{"__symbolic":"reference","name":"AccordionComponent"},{"__symbolic":"reference","name":"AccordionItemDirective"},{"__symbolic":"reference","name":"AccordionItemsDirective"}]}]}],"members":{}},"AccordionAllModule":{"__symbolic":"class","decorators":[{"__symbolic":"call","expression":{"__symbolic":"reference","module":"@angular/core","name":"NgModule"},"arguments":[{"imports":[{"__symbolic":"reference","module":"@angular/common","name":"CommonModule"},{"__symbolic":"reference","name":"AccordionModule"}],"exports":[{"__symbolic":"reference","name":"AccordionModule"}],"providers":[]}]}],"members":{}},"ItemDirective":{"__symbolic":"class","extends":{"__symbolic":"reference","module":"@syncfusion/ej2-angular-base","name":"ComplexBase"},"decorators":[{"__symbolic":"call","expression":{"__symbolic":"reference","module":"@angular/core","name":"Directive"},"arguments":[{"selector":"e-items>e-item","inputs":["align","cssClass","disabled","htmlAttributes","id","overflow","prefixIcon","showAlwaysInPopup","showTextOn","suffixIcon","template","text","tooltipText","type","visible","width"],"outputs":["click"],"queries":{}}]}],"members":{"template":[{"__symbolic":"property","decorators":[{"__symbolic":"call","expression":{"__symbolic":"reference","module":"@angular/core","name":"ContentChild"},"arguments":["template"]},{"__symbolic":"call","expression":{"__symbolic":"reference","module":"@syncfusion/ej2-angular-base","name":"Template"}}]}],"__ctor__":[{"__symbolic":"constructor","parameters":[{"__symbolic":"reference","module":"@angular/core","name":"ViewContainerRef"}]}]}},"ItemsDirective":{"__symbolic":"class","extends":{"__symbolic":"reference","module":"@syncfusion/ej2-angular-base","name":"ArrayBase"},"decorators":[{"__symbolic":"call","expression":{"__symbolic":"reference","module":"@angular/core","name":"Directive"},"arguments":[{"selector":"ejs-toolbar>e-items","queries":{"children":{"__symbolic":"new","expression":{"__symbolic":"reference","module":"@angular/core","name":"ContentChildren"},"arguments":[{"__symbolic":"reference","name":"ItemDirective"}]}}}]}],"members":{"__ctor__":[{"__symbolic":"constructor"}]}},"ToolbarComponent":{"__symbolic":"class","extends":{"__symbolic":"reference","module":"@syncfusion/ej2-navigations","name":"Toolbar"},"decorators":[{"__symbolic":"call","expression":{"__symbolic":"reference","module":"@angular/core","name":"Component"},"arguments":[{"selector":"ejs-toolbar","inputs":{"__symbolic":"reference","name":"ɵc"},"outputs":{"__symbolic":"reference","name":"ɵd"},"template":"<ng-content select='div'></ng-content>","changeDetection":{"__symbolic":"select","expression":{"__symbolic":"reference","module":"@angular/core","name":"ChangeDetectionStrategy"},"member":"OnPush"},"queries":{"childItems":{"__symbolic":"new","expression":{"__symbolic":"reference","module":"@angular/core","name":"ContentChild"},"arguments":[{"__symbolic":"reference","name":"ItemsDirective"}]}}}]},{"__symbolic":"call","expression":{"__symbolic":"reference","module":"@syncfusion/ej2-angular-base","name":"ComponentMixins"},"arguments":[[{"__symbolic":"reference","module":"@syncfusion/ej2-angular-base","name":"ComponentBase"}]]}],"members":{"__ctor__":[{"__symbolic":"constructor","parameters":[{"__symbolic":"reference","module":"@angular/core","name":"ElementRef"},{"__symbolic":"reference","module":"@angular/core","name":"Renderer2"},{"__symbolic":"reference","module":"@angular/core","name":"ViewContainerRef"},{"__symbolic":"reference","module":"@angular/core","name":"Injector"}]}],"ngOnInit":[{"__symbolic":"method"}],"ngAfterViewInit":[{"__symbolic":"method"}],"ngOnDestroy":[{"__symbolic":"method"}],"ngAfterContentChecked":[{"__symbolic":"method"}]}},"ToolbarModule":{"__symbolic":"class","decorators":[{"__symbolic":"call","expression":{"__symbolic":"reference","module":"@angular/core","name":"NgModule"},"arguments":[{"imports":[{"__symbolic":"reference","module":"@angular/common","name":"CommonModule"}],"declarations":[{"__symbolic":"reference","name":"ToolbarComponent"},{"__symbolic":"reference","name":"ItemDirective"},{"__symbolic":"reference","name":"ItemsDirective"}],"exports":[{"__symbolic":"reference","name":"ToolbarComponent"},{"__symbolic":"reference","name":"ItemDirective"},{"__symbolic":"reference","name":"ItemsDirective"}]}]}],"members":{}},"ToolbarAllModule":{"__symbolic":"class","decorators":[{"__symbolic":"call","expression":{"__symbolic":"reference","module":"@angular/core","name":"NgModule"},"arguments":[{"imports":[{"__symbolic":"reference","module":"@angular/common","name":"CommonModule"},{"__symbolic":"reference","name":"ToolbarModule"}],"exports":[{"__symbolic":"reference","name":"ToolbarModule"}],"providers":[]}]}],"members":{}},"ContextMenuComponent":{"__symbolic":"class","extends":{"__symbolic":"reference","module":"@syncfusion/ej2-navigations","name":"ContextMenu"},"decorators":[{"__symbolic":"call","expression":{"__symbolic":"reference","module":"@angular/core","name":"Component"},"arguments":[{"selector":"ejs-contextmenu","inputs":{"__symbolic":"reference","name":"ɵe"},"outputs":{"__symbolic":"reference","name":"ɵf"},"template":"","changeDetection":{"__symbolic":"select","expression":{"__symbolic":"reference","module":"@angular/core","name":"ChangeDetectionStrategy"},"member":"OnPush"},"queries":{}}]},{"__symbolic":"call","expression":{"__symbolic":"reference","module":"@syncfusion/ej2-angular-base","name":"ComponentMixins"},"arguments":[[{"__symbolic":"reference","module":"@syncfusion/ej2-angular-base","name":"ComponentBase"}]]}],"members":{"__ctor__":[{"__symbolic":"constructor","parameters":[{"__symbolic":"reference","module":"@angular/core","name":"ElementRef"},{"__symbolic":"reference","module":"@angular/core","name":"Renderer2"},{"__symbolic":"reference","module":"@angular/core","name":"ViewContainerRef"},{"__symbolic":"reference","module":"@angular/core","name":"Injector"}]}],"ngOnInit":[{"__symbolic":"method"}],"ngAfterViewInit":[{"__symbolic":"method"}],"ngOnDestroy":[{"__symbolic":"method"}],"ngAfterContentChecked":[{"__symbolic":"method"}]}},"ContextMenuModule":{"__symbolic":"class","decorators":[{"__symbolic":"call","expression":{"__symbolic":"reference","module":"@angular/core","name":"NgModule"},"arguments":[{"imports":[{"__symbolic":"reference","module":"@angular/common","name":"CommonModule"}],"declarations":[{"__symbolic":"reference","name":"ContextMenuComponent"}],"exports":[{"__symbolic":"reference","name":"ContextMenuComponent"}]}]}],"members":{}},"ContextMenuAllModule":{"__symbolic":"class","decorators":[{"__symbolic":"call","expression":{"__symbolic":"reference","module":"@angular/core","name":"NgModule"},"arguments":[{"imports":[{"__symbolic":"reference","module":"@angular/common","name":"CommonModule"},{"__symbolic":"reference","name":"ContextMenuModule"}],"exports":[{"__symbolic":"reference","name":"ContextMenuModule"}],"providers":[]}]}],"members":{}},"TabItemDirective":{"__symbolic":"class","extends":{"__symbolic":"reference","module":"@syncfusion/ej2-angular-base","name":"ComplexBase"},"decorators":[{"__symbolic":"call","expression":{"__symbolic":"reference","module":"@angular/core","name":"Directive"},"arguments":[{"selector":"e-tabitems>e-tabitem","inputs":["content","cssClass","disabled","header","headerTemplate","visible"],"outputs":[],"queries":{}}]}],"members":{"content":[{"__symbolic":"property","decorators":[{"__symbolic":"call","expression":{"__symbolic":"reference","module":"@angular/core","name":"ContentChild"},"arguments":["content"]},{"__symbolic":"call","expression":{"__symbolic":"reference","module":"@syncfusion/ej2-angular-base","name":"Template"}}]}],"header_text":[{"__symbolic":"property","decorators":[{"__symbolic":"call","expression":{"__symbolic":"reference","module":"@angular/core","name":"ContentChild"},"arguments":["headerText"]},{"__symbolic":"call","expression":{"__symbolic":"reference","module":"@syncfusion/ej2-angular-base","name":"Template"}}]}],"headerTemplate":[{"__symbolic":"property","decorators":[{"__symbolic":"call","expression":{"__symbolic":"reference","module":"@angular/core","name":"ContentChild"},"arguments":["headerTemplate"]},{"__symbolic":"call","expression":{"__symbolic":"reference","module":"@syncfusion/ej2-angular-base","name":"Template"}}]}],"__ctor__":[{"__symbolic":"constructor","parameters":[{"__symbolic":"reference","module":"@angular/core","name":"ViewContainerRef"}]}]}},"TabItemsDirective":{"__symbolic":"class","extends":{"__symbolic":"reference","module":"@syncfusion/ej2-angular-base","name":"ArrayBase"},"decorators":[{"__symbolic":"call","expression":{"__symbolic":"reference","module":"@angular/core","name":"Directive"},"arguments":[{"selector":"ejs-tab>e-tabitems","queries":{"children":{"__symbolic":"new","expression":{"__symbolic":"reference","module":"@angular/core","name":"ContentChildren"},"arguments":[{"__symbolic":"reference","name":"TabItemDirective"}]}}}]}],"members":{"__ctor__":[{"__symbolic":"constructor"}]}},"TabComponent":{"__symbolic":"class","extends":{"__symbolic":"reference","module":"@syncfusion/ej2-navigations","name":"Tab"},"decorators":[{"__symbolic":"call","expression":{"__symbolic":"reference","module":"@angular/core","name":"Component"},"arguments":[{"selector":"ejs-tab","inputs":{"__symbolic":"reference","name":"ɵg"},"outputs":{"__symbolic":"reference","name":"ɵh"},"template":"<ng-content select='div'></ng-content>","changeDetection":{"__symbolic":"select","expression":{"__symbolic":"reference","module":"@angular/core","name":"ChangeDetectionStrategy"},"member":"OnPush"},"queries":{"childItems":{"__symbolic":"new","expression":{"__symbolic":"reference","module":"@angular/core","name":"ContentChild"},"arguments":[{"__symbolic":"reference","name":"TabItemsDirective"}]}}}]},{"__symbolic":"call","expression":{"__symbolic":"reference","module":"@syncfusion/ej2-angular-base","name":"ComponentMixins"},"arguments":[[{"__symbolic":"reference","module":"@syncfusion/ej2-angular-base","name":"ComponentBase"}]]}],"members":{"__ctor__":[{"__symbolic":"constructor","parameters":[{"__symbolic":"reference","module":"@angular/core","name":"ElementRef"},{"__symbolic":"reference","module":"@angular/core","name":"Renderer2"},{"__symbolic":"reference","module":"@angular/core","name":"ViewContainerRef"},{"__symbolic":"reference","module":"@angular/core","name":"Injector"}]}],"ngOnInit":[{"__symbolic":"method"}],"ngAfterViewInit":[{"__symbolic":"method"}],"ngOnDestroy":[{"__symbolic":"method"}],"ngAfterContentChecked":[{"__symbolic":"method"}]}},"TabModule":{"__symbolic":"class","decorators":[{"__symbolic":"call","expression":{"__symbolic":"reference","module":"@angular/core","name":"NgModule"},"arguments":[{"imports":[{"__symbolic":"reference","module":"@angular/common","name":"CommonModule"}],"declarations":[{"__symbolic":"reference","name":"TabComponent"},{"__symbolic":"reference","name":"TabItemDirective"},{"__symbolic":"reference","name":"TabItemsDirective"}],"exports":[{"__symbolic":"reference","name":"TabComponent"},{"__symbolic":"reference","name":"TabItemDirective"},{"__symbolic":"reference","name":"TabItemsDirective"}]}]}],"members":{}},"TabAllModule":{"__symbolic":"class","decorators":[{"__symbolic":"call","expression":{"__symbolic":"reference","module":"@angular/core","name":"NgModule"},"arguments":[{"imports":[{"__symbolic":"reference","module":"@angular/common","name":"CommonModule"},{"__symbolic":"reference","name":"TabModule"}],"exports":[{"__symbolic":"reference","name":"TabModule"}],"providers":[]}]}],"members":{}},"TreeViewComponent":{"__symbolic":"class","extends":{"__symbolic":"reference","module":"@syncfusion/ej2-navigations","name":"TreeView"},"decorators":[{"__symbolic":"call","expression":{"__symbolic":"reference","module":"@angular/core","name":"Component"},"arguments":[{"selector":"ejs-treeview","inputs":{"__symbolic":"reference","name":"ɵi"},"outputs":{"__symbolic":"reference","name":"ɵj"},"template":"","changeDetection":{"__symbolic":"select","expression":{"__symbolic":"reference","module":"@angular/core","name":"ChangeDetectionStrategy"},"member":"OnPush"},"queries":{}}]},{"__symbolic":"call","expression":{"__symbolic":"reference","module":"@syncfusion/ej2-angular-base","name":"ComponentMixins"},"arguments":[[{"__symbolic":"reference","module":"@syncfusion/ej2-angular-base","name":"ComponentBase"}]]}],"members":{"nodeTemplate":[{"__symbolic":"property","decorators":[{"__symbolic":"call","expression":{"__symbolic":"reference","module":"@angular/core","name":"ContentChild"},"arguments":["nodeTemplate"]},{"__symbolic":"call","expression":{"__symbolic":"reference","module":"@syncfusion/ej2-angular-base","name":"Template"}}]}],"__ctor__":[{"__symbolic":"constructor","parameters":[{"__symbolic":"reference","module":"@angular/core","name":"ElementRef"},{"__symbolic":"reference","module":"@angular/core","name":"Renderer2"},{"__symbolic":"reference","module":"@angular/core","name":"ViewContainerRef"},{"__symbolic":"reference","module":"@angular/core","name":"Injector"}]}],"ngOnInit":[{"__symbolic":"method"}],"ngAfterViewInit":[{"__symbolic":"method"}],"ngOnDestroy":[{"__symbolic":"method"}],"ngAfterContentChecked":[{"__symbolic":"method"}]}},"TreeViewModule":{"__symbolic":"class","decorators":[{"__symbolic":"call","expression":{"__symbolic":"reference","module":"@angular/core","name":"NgModule"},"arguments":[{"imports":[{"__symbolic":"reference","module":"@angular/common","name":"CommonModule"}],"declarations":[{"__symbolic":"reference","name":"TreeViewComponent"}],"exports":[{"__symbolic":"reference","name":"TreeViewComponent"}]}]}],"members":{}},"TreeViewAllModule":{"__symbolic":"class","decorators":[{"__symbolic":"call","expression":{"__symbolic":"reference","module":"@angular/core","name":"NgModule"},"arguments":[{"imports":[{"__symbolic":"reference","module":"@angular/common","name":"CommonModule"},{"__symbolic":"reference","name":"TreeViewModule"}],"exports":[{"__symbolic":"reference","name":"TreeViewModule"}],"providers":[]}]}],"members":{}},"SidebarComponent":{"__symbolic":"class","extends":{"__symbolic":"reference","module":"@syncfusion/ej2-navigations","name":"Sidebar"},"decorators":[{"__symbolic":"call","expression":{"__symbolic":"reference","module":"@angular/core","name":"Component"},"arguments":[{"selector":"ejs-sidebar","inputs":{"__symbolic":"reference","name":"ɵk"},"outputs":{"__symbolic":"reference","name":"ɵl"},"template":"<ng-content ></ng-content>","changeDetection":{"__symbolic":"select","expression":{"__symbolic":"reference","module":"@angular/core","name":"ChangeDetectionStrategy"},"member":"OnPush"},"queries":{}}]},{"__symbolic":"call","expression":{"__symbolic":"reference","module":"@syncfusion/ej2-angular-base","name":"ComponentMixins"},"arguments":[[{"__symbolic":"reference","module":"@syncfusion/ej2-angular-base","name":"ComponentBase"}]]}],"members":{"__ctor__":[{"__symbolic":"constructor","parameters":[{"__symbolic":"reference","module":"@angular/core","name":"ElementRef"},{"__symbolic":"reference","module":"@angular/core","name":"Renderer2"},{"__symbolic":"reference","module":"@angular/core","name":"ViewContainerRef"},{"__symbolic":"reference","module":"@angular/core","name":"Injector"}]}],"ngOnInit":[{"__symbolic":"method"}],"ngAfterViewInit":[{"__symbolic":"method"}],"ngOnDestroy":[{"__symbolic":"method"}],"ngAfterContentChecked":[{"__symbolic":"method"}]}},"SidebarModule":{"__symbolic":"class","decorators":[{"__symbolic":"call","expression":{"__symbolic":"reference","module":"@angular/core","name":"NgModule"},"arguments":[{"imports":[{"__symbolic":"reference","module":"@angular/common","name":"CommonModule"}],"declarations":[{"__symbolic":"reference","name":"SidebarComponent"}],"exports":[{"__symbolic":"reference","name":"SidebarComponent"}]}]}],"members":{}},"SidebarAllModule":{"__symbolic":"class","decorators":[{"__symbolic":"call","expression":{"__symbolic":"reference","module":"@angular/core","name":"NgModule"},"arguments":[{"imports":[{"__symbolic":"reference","module":"@angular/common","name":"CommonModule"},{"__symbolic":"reference","name":"SidebarModule"}],"exports":[{"__symbolic":"reference","name":"SidebarModule"}],"providers":[]}]}],"members":{}},"MenuItemDirective":{"__symbolic":"class","extends":{"__symbolic":"reference","module":"@syncfusion/ej2-angular-base","name":"ComplexBase"},"decorators":[{"__symbolic":"call","expression":{"__symbolic":"reference","module":"@angular/core","name":"Directive"},"arguments":[{"selector":"ejs-menu>e-menu-items>e-menu-item>","inputs":["iconCss","id","items","separator","text","url"],"outputs":[],"queries":{}}]}],"members":{"__ctor__":[{"__symbolic":"constructor","parameters":[{"__symbolic":"reference","module":"@angular/core","name":"ViewContainerRef"}]}]}},"MenuItemsDirective":{"__symbolic":"class","extends":{"__symbolic":"reference","module":"@syncfusion/ej2-angular-base","name":"ArrayBase"},"decorators":[{"__symbolic":"call","expression":{"__symbolic":"reference","module":"@angular/core","name":"Directive"},"arguments":[{"selector":"ejs-menu>e-menu-items","queries":{"children":{"__symbolic":"new","expression":{"__symbolic":"reference","module":"@angular/core","name":"ContentChildren"},"arguments":[{"__symbolic":"reference","name":"MenuItemDirective"}]}}}]}],"members":{"__ctor__":[{"__symbolic":"constructor"}]}},"MenuComponent":{"__symbolic":"class","extends":{"__symbolic":"reference","module":"@syncfusion/ej2-navigations","name":"Menu"},"decorators":[{"__symbolic":"call","expression":{"__symbolic":"reference","module":"@angular/core","name":"Component"},"arguments":[{"selector":"ejs-menu","inputs":{"__symbolic":"reference","name":"ɵm"},"outputs":{"__symbolic":"reference","name":"ɵn"},"template":"","changeDetection":{"__symbolic":"select","expression":{"__symbolic":"reference","module":"@angular/core","name":"ChangeDetectionStrategy"},"member":"OnPush"},"queries":{"childItems":{"__symbolic":"new","expression":{"__symbolic":"reference","module":"@angular/core","name":"ContentChild"},"arguments":[{"__symbolic":"reference","name":"MenuItemsDirective"}]}}}]},{"__symbolic":"call","expression":{"__symbolic":"reference","module":"@syncfusion/ej2-angular-base","name":"ComponentMixins"},"arguments":[[{"__symbolic":"reference","module":"@syncfusion/ej2-angular-base","name":"ComponentBase"}]]}],"members":{"template":[{"__symbolic":"property","decorators":[{"__symbolic":"call","expression":{"__symbolic":"reference","module":"@angular/core","name":"ContentChild"},"arguments":["template"]},{"__symbolic":"call","expression":{"__symbolic":"reference","module":"@syncfusion/ej2-angular-base","name":"Template"}}]}],"__ctor__":[{"__symbolic":"constructor","parameters":[{"__symbolic":"reference","module":"@angular/core","name":"ElementRef"},{"__symbolic":"reference","module":"@angular/core","name":"Renderer2"},{"__symbolic":"reference","module":"@angular/core","name":"ViewContainerRef"},{"__symbolic":"reference","module":"@angular/core","name":"Injector"}]}],"ngOnInit":[{"__symbolic":"method"}],"ngAfterViewInit":[{"__symbolic":"method"}],"ngOnDestroy":[{"__symbolic":"method"}],"ngAfterContentChecked":[{"__symbolic":"method"}]}},"MenuModule":{"__symbolic":"class","decorators":[{"__symbolic":"call","expression":{"__symbolic":"reference","module":"@angular/core","name":"NgModule"},"arguments":[{"imports":[{"__symbolic":"reference","module":"@angular/common","name":"CommonModule"}],"declarations":[{"__symbolic":"reference","name":"MenuComponent"},{"__symbolic":"reference","name":"MenuItemDirective"},{"__symbolic":"reference","name":"MenuItemsDirective"}],"exports":[{"__symbolic":"reference","name":"MenuComponent"},{"__symbolic":"reference","name":"MenuItemDirective"},{"__symbolic":"reference","name":"MenuItemsDirective"}]}]}],"members":{}},"MenuAllModule":{"__symbolic":"class","decorators":[{"__symbolic":"call","expression":{"__symbolic":"reference","module":"@angular/core","name":"NgModule"},"arguments":[{"imports":[{"__symbolic":"reference","module":"@angular/common","name":"CommonModule"},{"__symbolic":"reference","name":"MenuModule"}],"exports":[{"__symbolic":"reference","name":"MenuModule"}],"providers":[]}]}],"members":{}}},"origins":{"ɵa":"./src/accordion/accordion.component","ɵb":"./src/accordion/accordion.component","ɵc":"./src/toolbar/toolbar.component","ɵd":"./src/toolbar/toolbar.component","ɵe":"./src/context-menu/contextmenu.component","ɵf":"./src/context-menu/contextmenu.component","ɵg":"./src/tab/tab.component","ɵh":"./src/tab/tab.component","ɵi":"./src/treeview/treeview.component","ɵj":"./src/treeview/treeview.component","ɵk":"./src/sidebar/sidebar.component","ɵl":"./src/sidebar/sidebar.component","ɵm":"./src/menu/menu.component","ɵn":"./src/menu/menu.component","AccordionItemDirective":"./src/accordion/items.directive","AccordionItemsDirective":"./src/accordion/items.directive","AccordionComponent":"./src/accordion/accordion.component","AccordionModule":"./src/accordion/accordion.module","AccordionAllModule":"./src/accordion/accordion-all.module","ItemDirective":"./src/toolbar/items.directive","ItemsDirective":"./src/toolbar/items.directive","ToolbarComponent":"./src/toolbar/toolbar.component","ToolbarModule":"./src/toolbar/toolbar.module","ToolbarAllModule":"./src/toolbar/toolbar-all.module","ContextMenuComponent":"./src/context-menu/contextmenu.component","ContextMenuModule":"./src/context-menu/contextmenu.module","ContextMenuAllModule":"./src/context-menu/contextmenu-all.module","TabItemDirective":"./src/tab/items.directive","TabItemsDirective":"./src/tab/items.directive","TabComponent":"./src/tab/tab.component","TabModule":"./src/tab/tab.module","TabAllModule":"./src/tab/tab-all.module","TreeViewComponent":"./src/treeview/treeview.component","TreeViewModule":"./src/treeview/treeview.module","TreeViewAllModule":"./src/treeview/treeview-all.module","SidebarComponent":"./src/sidebar/sidebar.component","SidebarModule":"./src/sidebar/sidebar.module","SidebarAllModule":"./src/sidebar/sidebar-all.module","MenuItemDirective":"./src/menu/items.directive","MenuItemsDirective":"./src/menu/items.directive","MenuComponent":"./src/menu/menu.component","MenuModule":"./src/menu/menu.module","MenuAllModule":"./src/menu/menu-all.module"},"importAs":"@syncfusion/ej2-angular-navigations"}